{
  "$schema": "https://raw.githubusercontent.com/spdx/spdx-spec/v2.2.1/schemas/spdx-schema.json",
  "spdxVersion": "SPDX-2.2",
  "dataLicense": "CC0-1.0",
  "SPDXID": "SPDXRef-DOCUMENT",
  "documentNamespace": "https://spdx.org/spdxdocs/boost-serialization-arm64-osx-1.85.0#1-be9661fc-b698-4842-bc28-5b4572e93df5",
  "name": "boost-serialization:arm64-osx@1.85.0#1 c7b0ddaac35a290f8e36fc5b1fac899a8f4f7919912d35bf9af2c22e31282f2c",
  "creationInfo": {
    "creators": [
      "Tool: vcpkg-d6945642ee5c3076addd1a42c331bbf4cfc97457"
    ],
    "created": "2024-08-08T16:31:37Z"
  },
  "relationships": [
    {
      "spdxElementId": "SPDXRef-port",
      "relationshipType": "GENERATES",
      "relatedSpdxElement": "SPDXRef-binary"
    },
    {
      "spdxElementId": "SPDXRef-port",
      "relationshipType": "CONTAINS",
      "relatedSpdxElement": "SPDXRef-file-0"
    },
    {
      "spdxElementId": "SPDXRef-port",
      "relationshipType": "CONTAINS",
      "relatedSpdxElement": "SPDXRef-file-1"
    },
    {
      "spdxElementId": "SPDXRef-binary",
      "relationshipType": "GENERATED_FROM",
      "relatedSpdxElement": "SPDXRef-port"
    },
    {
      "spdxElementId": "SPDXRef-file-0",
      "relationshipType": "CONTAINED_BY",
      "relatedSpdxElement": "SPDXRef-port"
    },
    {
      "spdxElementId": "SPDXRef-file-1",
      "relationshipType": "CONTAINED_BY",
      "relatedSpdxElement": "SPDXRef-port"
    }
  ],
  "packages": [
    {
      "name": "boost-serialization",
      "SPDXID": "SPDXRef-port",
      "versionInfo": "1.85.0#1",
      "downloadLocation": "NOASSERTION",
      "homepage": "https://www.boost.org/libs/serialization",
      "licenseConcluded": "BSL-1.0",
      "licenseDeclared": "NOASSERTION",
      "copyrightText": "NOASSERTION",
      "description": "Boost serialization module",
      "comment": "This is the port (recipe) consumed by vcpkg."
    },
    {
      "name": "boost-serialization:arm64-osx",
      "SPDXID": "SPDXRef-binary",
      "versionInfo": "c7b0ddaac35a290f8e36fc5b1fac899a8f4f7919912d35bf9af2c22e31282f2c",
      "downloadLocation": "NONE",
      "licenseConcluded": "BSL-1.0",
      "licenseDeclared": "NOASSERTION",
      "copyrightText": "NOASSERTION",
      "comment": "This is a binary package built by vcpkg."
    },
    {
      "SPDXID": "SPDXRef-resource-1",
      "name": "boostorg/serialization",
      "downloadLocation": "git+https://github.com/boostorg/serialization@boost-1.85.0",
      "licenseConcluded": "NOASSERTION",
      "licenseDeclared": "NOASSERTION",
      "copyrightText": "NOASSERTION",
      "checksums": [
        {
          "algorithm": "SHA512",
          "checksumValue": "c338064f8c191547da5823f226d1ec1b8b36458a588dbc22e738936a05fde772681bce5c82340b628a7d7b9c45b646d491c18444d1e352d34854de37f107a963"
        }
      ]
    }
  ],
  "files": [
    {
      "fileName": ".//Users/guillaume/dev/client/vcpkg/ports/boost-serialization/portfile.cmake",
      "SPDXID": "SPDXRef-file-0",
      "checksums": [
        {
          "algorithm": "SHA256",
          "checksumValue": "14388cc9c6e4b893c6ec872172b4eb07793016c5bc7bdce7b4ca4312d877792d"
        }
      ],
      "licenseConcluded": "NOASSERTION",
      "copyrightText": "NOASSERTION"
    },
    {
      "fileName": ".//Users/guillaume/dev/client/vcpkg/ports/boost-serialization/vcpkg.json",
      "SPDXID": "SPDXRef-file-1",
      "checksums": [
        {
          "algorithm": "SHA256",
          "checksumValue": "7457d04b6f88181fd888140cdfdfb832fc46e65e142c9f22584c884a8fbd85b6"
        }
      ],
      "licenseConcluded": "NOASSERTION",
      "copyrightText": "NOASSERTION"
    }
  ]
}
